[
    {
        "A": 1.35742e-6,
        "B": 4.80389020993,
        "C": 10213.285546211
    },
    {
        "A": 7.7846e-7,
        "B": 3.66876371591,
        "C": 20426.571092422
    },
    {
        "A": 2.6023e-7,
        "B": 0,
        "C": 0
    },
    {
        "A": 1.214e-8,
        "B": 5.31970006917,
        "C": 30639.856638633
    },
    {
        "A": 2.54e-9,
        "B": 4.15021671822,
        "C": 40853.142184844
    },
    {
        "A": 8.0e-11,
        "B": 5.55523563261,
        "C": 51066.427731055
    },
    {
        "A": 8.0e-11,
        "B": 1.40501229148,
        "C": 1577.3435424478
    },
    {
        "A": 6.0e-11,
        "B": 1.27791479726,
        "C": 10404.7338123226
    }
]